visualdecimal/__init__.py
visualdecimal/expression.py
visualdecimal/expression_test.py
visualdecimal/v2/__init__.py
visualdecimal/v2/expression.py
visualdecimal/v2/expression_test.py
visual_decimal-1.1.0.dist-info/METADATA
visual_decimal-1.1.0.dist-info/WHEEL
visual_decimal-1.1.0.dist-info/licenses/LICENSE
visual_decimal-1.1.0.dist-info/RECORD
